pylonguy/__init__.py
pylonguy/camera.py
pylonguy/constants.py
pylonguy/main.py
pylonguy/thread.py
pylonguy/worker.py
pylonguy/wtf2png.py
pylonguy/assets/icon.ico
pylonguy/gui/__init__.py
pylonguy/gui/log.py
pylonguy/gui/preview.py
pylonguy/gui/settings.py
pylonguy-1.9.0.dist-info/METADATA
pylonguy-1.9.0.dist-info/WHEEL
pylonguy-1.9.0.dist-info/entry_points.txt
pylonguy-1.9.0.dist-info/licenses/LICENSE
pylonguy-1.9.0.dist-info/RECORD
