Metadata-Version: 2.4
Name: pylonguy
Version: 1.9.0
Summary: PyQt5 wrapper for pypylon SDK for Basler camera manipulation, aimed for microfluidics and slow motion.
Project-URL: Repository, https://github.com/merv1n34k/pylonguy
License-Expression: MIT
License-File: LICENSE
Requires-Python: >=3.12
Requires-Dist: numpy>=2.3.3
Requires-Dist: pillow>=11.3.0
Requires-Dist: pypylon>=4.2.0
Requires-Dist: pyqt5>=5.15.11
